gerrit/__init__.py
gerrit/base.py
gerrit/accounts/__init__.py
gerrit/accounts/account.py
gerrit/accounts/accounts.py
gerrit/accounts/emails.py
gerrit/accounts/gpg_keys.py
gerrit/accounts/ssh_keys.py
gerrit/changes/__init__.py
gerrit/changes/change.py
gerrit/changes/changes.py
gerrit/changes/comments.py
gerrit/changes/drafts.py
gerrit/changes/edit.py
gerrit/changes/files.py
gerrit/changes/messages.py
gerrit/changes/reviewers.py
gerrit/changes/revision.py
gerrit/config/__init__.py
gerrit/config/caches.py
gerrit/config/config.py
gerrit/config/tasks.py
gerrit/groups/__init__.py
gerrit/groups/group.py
gerrit/groups/groups.py
gerrit/groups/members.py
gerrit/groups/subgroups.py
gerrit/plugins/__init__.py
gerrit/plugins/plugins.py
gerrit/projects/__init__.py
gerrit/projects/branches.py
gerrit/projects/commit.py
gerrit/projects/dashboards.py
gerrit/projects/labels.py
gerrit/projects/project.py
gerrit/projects/projects.py
gerrit/projects/tags.py
gerrit/projects/webhooks.py
gerrit/utils/__init__.py
gerrit/utils/common.py
gerrit/utils/exceptions.py
gerrit/utils/gerritbase.py
gerrit/utils/requester.py
gitiles/__init__.py
gitiles/base.py
python_gerrit_api-3.0.8.dist-info/LICENSE
python_gerrit_api-3.0.8.dist-info/METADATA
python_gerrit_api-3.0.8.dist-info/WHEEL
python_gerrit_api-3.0.8.dist-info/top_level.txt
python_gerrit_api-3.0.8.dist-info/RECORD
