Metadata-Version: 2.1
Name: python-gerrit-api
Version: 3.0.8
Summary: Python wrapper for the Gerrit REST API.
Home-page: https://github.com/shijl0925/python-gerrit-api
Author: Jialiang Shi
Author-email: kevin09254930sjl@gmail.com
License: MIT
Keywords: api gerrit client wrapper
Classifier: Development Status :: 5 - Production/Stable
Classifier: Environment :: Plugins
Classifier: Intended Audience :: Developers
Classifier: License :: OSI Approved :: MIT License
Classifier: Operating System :: OS Independent
Classifier: Programming Language :: Python :: 3.6
Classifier: Programming Language :: Python :: 3.7
Classifier: Programming Language :: Python :: 3.8
Classifier: Programming Language :: Python :: 3.9
Classifier: Programming Language :: Python :: 3.10
Classifier: Programming Language :: Python :: 3.11
Classifier: Programming Language :: Python :: 3.12
Classifier: Topic :: Software Development
License-File: LICENSE
Requires-Dist: requests
